LICENSE
README.md
pyproject.toml
setup.py
src/verify4py/Issuer.py
src/verify4py/JsonIssuer.py
src/verify4py/PdfIssuer.py
src/verify4py/UniversityDiplomaIssuer.py
src/verify4py/__init__.py
src/verify4py/certify_sc_utils.py
src/verify4py/json_utils.py
src/verify4py/pdf.py
src/verify4py/test_UniversityDiplomaIssuer.py
src/verify4py/university_abi.py
src/verify4py/utils.py
src/verify4py_test1.egg-info/PKG-INFO
src/verify4py_test1.egg-info/SOURCES.txt
src/verify4py_test1.egg-info/dependency_links.txt
src/verify4py_test1.egg-info/requires.txt
src/verify4py_test1.egg-info/top_level.txt