Metadata-Version: 2.1
Name: verify4py-test1
Version: 1.0.2
Summary: Issue certificates using blockchain and smart contract
Home-page: https://github.com/teo-mn/verify4py
Author: Surenbayar Doloonjin
Author-email: surenbayar@corex.mn
License: UNKNOWN
Project-URL: Bug Tracker, https://github.com/teo-mn/verify4py/issues
Platform: UNKNOWN
Classifier: Programming Language :: Python :: 3
Classifier: License :: OSI Approved :: MIT License
Classifier: Operating System :: OS Independent
Requires-Python: >=3.6
License-File: LICENSE
